<?xml version="1.0" encoding="UTF-8" ?>
<class name="DiscordAuthorizationArgs" inherits="RefCounted" xmlns:xsi="http://www.w3.org/2001/XMLSchema-instance" xsi:noNamespaceSchemaLocation="https://raw.githubusercontent.com/godotengine/godot/master/doc/class.xsd">
	<brief_description>
	</brief_description>
	<description>
	</description>
	<tutorials>
	</tutorials>
	<methods>
		<method name="client_id">
			<return type="int" />
			<description>
			</description>
		</method>
		<method name="code_challenge">
			<return type="Variant" />
			<description>
			</description>
		</method>
		<method name="custom_scheme_param">
			<return type="Variant" />
			<description>
			</description>
		</method>
		<method name="integration_type">
			<return type="Variant" />
			<description>
			</description>
		</method>
		<method name="nonce">
			<return type="Variant" />
			<description>
			</description>
		</method>
		<method name="scopes">
			<return type="String" />
			<description>
			</description>
		</method>
		<method name="set_client_id">
			<return type="void" />
			<param index="0" name="client_id" type="int" />
			<description>
			</description>
		</method>
		<method name="set_code_challenge">
			<return type="void" />
			<param index="0" name="code_challenge" type="Variant" />
			<description>
			</description>
		</method>
		<method name="set_custom_scheme_param">
			<return type="void" />
			<param index="0" name="custom_scheme_param" type="Variant" />
			<description>
			</description>
		</method>
		<method name="set_integration_type">
			<return type="void" />
			<param index="0" name="integration_type" type="Variant" />
			<description>
			</description>
		</method>
		<method name="set_nonce">
			<return type="void" />
			<param index="0" name="nonce" type="Variant" />
			<description>
			</description>
		</method>
		<method name="set_scopes">
			<return type="void" />
			<param index="0" name="scopes" type="String" />
			<description>
			</description>
		</method>
		<method name="set_state">
			<return type="void" />
			<param index="0" name="state" type="Variant" />
			<description>
			</description>
		</method>
		<method name="state">
			<return type="Variant" />
			<description>
			</description>
		</method>
	</methods>
</class>
